lib_dzne_seq/__init__.py
lib_dzne_seq-0.2.6.dist-info/LICENSE.txt
lib_dzne_seq-0.2.6.dist-info/METADATA
lib_dzne_seq-0.2.6.dist-info/WHEEL
lib_dzne_seq-0.2.6.dist-info/top_level.txt
lib_dzne_seq-0.2.6.dist-info/RECORD
