Metadata-Version: 2.1
Name: lib-dzne-seq
Version: 0.2.6
Summary: Libary for handling genetic sequences.
Author-email: Johannes Programming <johannes-programming@posteo.org>
License: The MIT License (MIT)
Project-URL: Source, https://github.com/johannes-programming/lib_dzne_seq
Project-URL: Download, https://pypi.org/project/lib-dzne-seq/#files
Classifier: License :: OSI Approved :: MIT License
Classifier: Programming Language :: Python
Classifier: Programming Language :: Python :: 3
Requires-Python: >=3.11
License-File: LICENSE.txt
Requires-Dist: Bio >=1.5.3
Requires-Dist: gravy >=1.0.0
Requires-Dist: seqpad >=1.0.0
Requires-Dist: lib-dzne-filedata >=0.4.0
Requires-Dist: na-quantors >=1.0.0
